clabe/__init__.py
clabe/banks.py
clabe/py.typed
clabe/types.py
clabe/validations.py
clabe/version.py
tests/__init__.py
tests/test_clabe.py
tests/test_types.py
clabe-2.1.7.dist-info/LICENSE
clabe-2.1.7.dist-info/METADATA
clabe-2.1.7.dist-info/WHEEL
clabe-2.1.7.dist-info/top_level.txt
clabe-2.1.7.dist-info/RECORD
