Metadata-Version: 2.1
Name: clabe
Version: 2.1.7
Summary: Validate and generate the control digit of a CLABE in Mexico
Home-page: https://github.com/cuenca-mx/clabe
Author: Cuenca
Author-email: dev@cuenca.com
Classifier: Programming Language :: Python :: 3
Classifier: License :: OSI Approved :: MIT License
Classifier: Operating System :: OS Independent
Requires-Python: >=3.8
License-File: LICENSE
Requires-Dist: pydantic>=2.10.3
